pyctorize/__init__.py
pyctorize/pyctorize.py
pyctorize-2.0.dist-info/LICENSE
pyctorize-2.0.dist-info/METADATA
pyctorize-2.0.dist-info/WHEEL
pyctorize-2.0.dist-info/entry_points.txt
pyctorize-2.0.dist-info/top_level.txt
pyctorize-2.0.dist-info/RECORD
