Metadata-Version: 2.1
Name: pyctorize
Version: 2.0
Summary: A Python CLI program to extract frames of videos
Home-page: https://github.com/vccolombo/pyctorize
Author: Víctor Cora Colombo
License: UNKNOWN
Platform: UNKNOWN
Classifier: Development Status :: 5 - Production/Stable
Classifier: Environment :: Console
Classifier: Programming Language :: Python :: 3
Classifier: Programming Language :: Python :: 3.7
Classifier: License :: OSI Approved :: MIT License
Requires-Dist: click (==7.0)
Requires-Dist: moviepy (==1.0.0)
